zoterotex/__init__.py
zoterotex/__main__.py
zoterotex/_sync.py
zoterotex-0.1.1.dist-info/METADATA
zoterotex-0.1.1.dist-info/WHEEL
zoterotex-0.1.1.dist-info/entry_points.txt
zoterotex-0.1.1.dist-info/top_level.txt
zoterotex-0.1.1.dist-info/RECORD
