Metadata-Version: 2.1
Name: zoterotex
Version: 0.1.1
Summary: Wrapper for [`pyzotero`](https://github.com/urschrei/pyzotero) that keeps a BibTeX file in sync with a Zotero library.
Author-email: Robert Gale <rcgale@gmail.com>
Project-URL: homepage, https://github.com/rcgale/zoterotex
Project-URL: repository, https://github.com/rcgale/zoterotex
Requires-Python: >=3.9
Requires-Dist: pyzotero (~=1.5)
Requires-Dist: bibtexparser (~=1.4)
